{
 "absolute_value": 0,
 "align_labels_right": 0,
 "creation": "2023-03-08 21:33:00.353073",
 "css": "@font-face {\n  font-family: SourceSansPro;\n  src: url(SourceSansPro-Regular.ttf);\n}\n\n.clearfix:after {\n  content: \"\";\n  display: table;\n  clear: both;\n}\n\na {\n  color: #0087C3;\n  text-decoration: none;\n}\n\nbody {\n  position: relative;\n  width: 21cm;  \n  height: 29.7cm; \n  margin: 0 auto; \n  color: #555555;\n  background: #FFFFFF; \n  font-family: Arial, sans-serif; \n  font-size: 14px; \n  font-family: SourceSansPro;\n}\n\nheader {\n  padding: 10px 0;\n  margin-bottom: 20px;\n  border-bottom: 1px solid #AAAAAA;\n}\n\n#logo {\n  float: left;\n  margin-top: 8px;\n}\n\n#logo img {\n  height: 70px;\n}\n\n#company {\n  float: right;\n  text-align: right;\n}\n\n\n#details {\n  margin-bottom: 50px;\n}\n\n#client {\n  padding-left: 6px;\n  border-left: 6px solid #0087C3;\n  float: left;\n}\n\n#client .to {\n  color: #777777;\n}\n\nh2.name {\n  font-size: 1.4em;\n  font-weight: normal;\n  margin: 0;\n}\n\n#invoice {\n  float: right;\n  text-align: right;\n}\n\n#invoice h1 {\n  color: #0087C3;\n  font-size: 2.4em;\n  line-height: 1em;\n  font-weight: normal;\n  margin: 0  0 10px 0;\n}\n\n#invoice .date {\n  font-size: 1.1em;\n  color: #777777;\n}\n\ntable {\n  width: 100%;\n  border-collapse: collapse;\n  border-spacing: 0;\n  margin-bottom: 20px;\n}\n\ntable th,\ntable td {\n  padding: 20px;\n  background: #EEEEEE;\n  text-align: center;\n  border-bottom: 1px solid #FFFFFF;\n}\n\ntable th {\n  white-space: nowrap;        \n  font-weight: normal;\n}\n\ntable td {\n  text-align: right;\n}\n\ntable td h3{\n  color: #57B223;\n  font-size: 1.2em;\n  font-weight: normal;\n  margin: 0 0 0.2em 0;\n}\n\ntable .no {\n \n  font-size: 1.6em;\n  background: #57B223;\n}\n\ntable .desc {\n  text-align: left;\n}\n\ntable .unit {\n  background: #DDDDDD;\n}\n\ntable .qty {\n}\n\ntable .total {\n  background: #57B223;\n\n}\n\ntable td.unit,\ntable td.qty,\ntable td.total {\n  font-size: 1.2em;\n}\n\ntable tbody tr:last-child td {\n  border: none;\n}\n\ntable tfoot td {\n  padding: 10px 20px;\n  background: #FFFFFF;\n  border-bottom: none;\n  font-size: 1.2em;\n  white-space: nowrap; \n  border-top: 1px solid #AAAAAA; \n}\n\ntable tfoot tr:first-child td {\n  border-top: none; \n}\n\ntable tfoot tr:last-child td {\n  color: #57B223;\n  font-size: 1.4em;\n  border-top: 1px solid #57B223; \n\n}\n\ntable tfoot tr td:first-child {\n  border: none;\n}\n\n#thanks{\n  font-size: 2em;\n  margin-bottom: 50px;\n}\n\n#notices{\n  padding-left: 6px;\n  border-left: 6px solid #0087C3;  \n}\n\n#notices .notice {\n  font-size: 1.2em;\n}\n\nfooter {\n  color: #777777;\n  width: 100%;\n  height: 30px;\n  position: absolute;\n  bottom: 0;\n  border-top: 1px solid #AAAAAA;\n  padding: 8px 0;\n  text-align: center;\n}\n\n",
 "custom_format": 1,
 "default_print_language": "en",
 "disabled": 0,
 "doc_type": "Sales Invoice",
 "docstatus": 0,
 "doctype": "Print Format",
 "font": "Default",
 "format_data": "[{\"fieldname\": \"print_heading_template\", \"fieldtype\": \"Custom HTML\", \"options\": \"<div class=\\\"print-heading\\\">\\t\\t\\t\\n<h2><div>Sales Invoice</div><br>\\n<small class=\\\"sub-heading\\\">{{ doc.name }}</small>\\n</h2></div>\"}, {\"fieldtype\": \"Section Break\", \"label\": \"\"}, {\"fieldtype\": \"Column Break\"}, {\"fieldname\": \"customer_name\", \"print_hide\": 0, \"label\": \"Customer Name\"}, {\"fieldtype\": \"Column Break\"}, {\"fieldname\": \"posting_date\", \"print_hide\": 0, \"label\": \"Date\"}, {\"fieldtype\": \"Section Break\", \"label\": \"Accounting Dimensions\"}, {\"fieldtype\": \"Column Break\"}, {\"fieldtype\": \"Column Break\"}, {\"fieldname\": \"cost_center\", \"print_hide\": 0, \"label\": \"Cost Center\"}, {\"fieldtype\": \"Section Break\", \"label\": \"Customer PO Details\"}, {\"fieldtype\": \"Column Break\"}, {\"fieldtype\": \"Column Break\"}, {\"fieldname\": \"po_date\", \"print_hide\": 0, \"label\": \"Customer's Purchase Order Date\"}, {\"fieldtype\": \"Section Break\", \"label\": \"Address and Contact\"}, {\"fieldtype\": \"Column Break\"}, {\"fieldname\": \"address_display\", \"print_hide\": 0, \"label\": \"Address\"}, {\"fieldname\": \"contact_display\", \"print_hide\": 0, \"label\": \"Contact\"}, {\"fieldname\": \"contact_mobile\", \"print_hide\": 0, \"label\": \"Mobile No\"}, {\"fieldtype\": \"Column Break\"}, {\"fieldname\": \"dispatch_address\", \"print_hide\": 0, \"label\": \"Dispatch Address\"}, {\"fieldtype\": \"Section Break\", \"label\": \"\"}, {\"fieldtype\": \"Column Break\"}, {\"fieldname\": \"items\", \"print_hide\": 0, \"label\": \"Items\", \"visible_columns\": [{\"fieldname\": \"item_code\", \"print_width\": \"\", \"print_hide\": 0}, {\"fieldname\": \"qty\", \"print_width\": \"\", \"print_hide\": 0}, {\"fieldname\": \"rate\", \"print_width\": \"\", \"print_hide\": 0}, {\"fieldname\": \"amount\", \"print_width\": \"\", \"print_hide\": 0}]}, {\"fieldtype\": \"Section Break\", \"label\": \"\"}, {\"fieldtype\": \"Column Break\"}, {\"fieldname\": \"total_qty\", \"print_hide\": 0, \"label\": \"Total Quantity\"}, {\"fieldtype\": \"Column Break\"}, {\"fieldname\": \"total\", \"print_hide\": 0, \"label\": \"Total\"}, {\"fieldtype\": \"Section Break\", \"label\": \"\"}, {\"fieldtype\": \"Column Break\"}, {\"fieldname\": \"taxes\", \"print_hide\": 0, \"label\": \"Sales Taxes and Charges\", \"visible_columns\": [{\"fieldname\": \"charge_type\", \"print_width\": \"\", \"print_hide\": 0}, {\"fieldname\": \"row_id\", \"print_width\": \"\", \"print_hide\": 0}, {\"fieldname\": \"account_head\", \"print_width\": \"\", \"print_hide\": 0}, {\"fieldname\": \"description\", \"print_width\": \"300px\", \"print_hide\": 0}, {\"fieldname\": \"included_in_paid_amount\", \"print_width\": \"\", \"print_hide\": 0}, {\"fieldname\": \"cost_center\", \"print_width\": \"\", \"print_hide\": 0}, {\"fieldname\": \"rate\", \"print_width\": \"\", \"print_hide\": 0}, {\"fieldname\": \"account_currency\", \"print_width\": \"\", \"print_hide\": 0}, {\"fieldname\": \"tax_amount\", \"print_width\": \"\", \"print_hide\": 0}, {\"fieldname\": \"total\", \"print_width\": \"\", \"print_hide\": 0}, {\"fieldname\": \"tax_amount_after_discount_amount\", \"print_width\": \"\", \"print_hide\": 0}, {\"fieldname\": \"base_tax_amount\", \"print_width\": \"\", \"print_hide\": 0}, {\"fieldname\": \"base_total\", \"print_width\": \"\", \"print_hide\": 0}, {\"fieldname\": \"base_tax_amount_after_discount_amount\", \"print_width\": \"\", \"print_hide\": 0}, {\"fieldname\": \"item_wise_tax_detail\", \"print_width\": \"\", \"print_hide\": 0}]}, {\"fieldtype\": \"Section Break\", \"label\": \"\"}, {\"fieldtype\": \"Column Break\"}, {\"fieldtype\": \"Column Break\"}, {\"fieldname\": \"grand_total\", \"print_hide\": 0, \"label\": \"Grand Total\"}]",
 "html": "<!DOCTYPE html>\n<html lang=\"en\">\n  <head>\n      <style>\nimg {\n  display: block;\n  margin-left: auto;\n  margin-right: auto;\n}\n</style>\n    <meta charset=\"utf-8\">\n    <link rel=\"stylesheet\" href=\"style.css\" media=\"all\" />\n  </head>\n  <body>\n    <header class=\"clearfix\">\n   <div id=\"company\">\n        <div><img src=\"http://185.177.57.155:8000/private/files/logo-1933884_1280-768x647.png\" style=\"width:15%\"></div>\n        <h2 class=\"name\">{{doc.company}}</h2>\n        <div>{{doc.company_address}}</div>\n        <div>(602) 519-0450</div>\n        <div><a href=\"mailto:company@example.com\">company@example.com</a></div>\n      </div>\n      \n    </header>\n    <main>\n      <div id=\"details\" class=\"clearfix\">\n        <div id=\"client\">\n          <div><img src=\"https://api.qrserver.com/v1/create-qr-code/?size=150x150&data={{doc.customer_name}} | {{doc.total}} ILS\" style=\"width:20%\"></div>\n          <div class=\"to\">INVOICE TO:</div>\n          <h2 class=\"name\">{{doc.customer_name}}</h2>\n          <div class=\"address\">{{doc.customer_address}}</div>\n        </div>\n         \n        <div id=\"invoice\">\n          <h1>INVOICE</h1>\n          <div class=\"date\">Date of Invoice: {{doc.posting_date}}</div>\n          <div class=\"date\">Due Date: {{doc.due_date}}</div>\n        </div>\n      </div>\n      <table border=\"0\" cellspacing=\"0\" cellpadding=\"0\">\n        <thead>\n          <tr>\n            <th class=\"no\">#</th>\n            <th class=\"desc\">DESCRIPTION</th>\n            <th class=\"unit\">UNIT PRICE</th>\n            <th class=\"qty\">QUANTITY</th>\n            <th class=\"total\">TOTAL</th>\n          </tr>\n        </thead>\n        <tbody>\n        {%- for row in doc.items -%}\n\t\t<tr>\n\t\t<td class=\"no\">{{ row.idx }}</td>\n\t\t<td class=\"desc\"><h3>{{ row.item_name }}</h3>{% if row.item_code != row.item_name -%}<br>Item Code: {{ row.item_code}}{%- endif %}</td>\n\t\t<td class=\"unit\">{{row.get_formatted(\"rate\", doc) }}</td>\n\t\t<td class=\"qty\">{{ row.qty }} </td>\n\t\t<td class=\"total\">{{row.get_formatted(\"amount\", doc) }}</td>\n\t\t</tr>\n\t\t{%- endfor -%}\n        </tbody>\n        <tfoot>\n          <tr>\n            <td colspan=\"2\"></td>\n            <td colspan=\"2\">SUBTOTAL</td>\n            <td>{{doc.total}}</td>\n          </tr>\n          <tr>\n            <td colspan=\"2\"></td>\n            <td colspan=\"2\">TAX 16%</td>\n            <td>{{doc.total_taxes_and_charges}}</td>\n          </tr>\n          <tr>\n            <td colspan=\"2\"></td>\n            <td colspan=\"2\">GRAND TOTAL</td>\n            <td>{{doc.grand_total}}</td>\n          </tr>\n        </tfoot>\n      </table>\n      <div id=\"thanks\">Thank you for your business !</div>\n      <div id=\"notices\">\n        <div>NOTICE:</div>\n        <div class=\"notice\">A finance charge of 1.5% will be made on unpaid balances after 30 days.</div>\n      </div>\n    </main>\n    <footer>\n      Invoice was created on a computer and is valid without the signature and seal.\n    </footer>\n  </body>\n</html>",
 "idx": 0,
 "line_breaks": 0,
 "modified": "2023-03-10 18:09:57.419692",
 "modified_by": "Administrator",
 "module": "erpnext_gsg",
 "name": "sales_invoice_gsg",
 "owner": "Administrator",
 "parent": "Sales Invoice",
 "print_format_builder": 0,
 "print_format_type": "Jinja",
 "raw_printing": 0,
 "show_section_headings": 0,
 "standard": "Yes"
}